precice_config_visualizer-2.0.0.dist-info/licenses/LICENSE
preciceconfigvisualizer/cli.py
preciceconfigvisualizer/common.py
precice_config_visualizer-2.0.0.dist-info/METADATA
precice_config_visualizer-2.0.0.dist-info/WHEEL
precice_config_visualizer-2.0.0.dist-info/entry_points.txt
precice_config_visualizer-2.0.0.dist-info/top_level.txt
precice_config_visualizer-2.0.0.dist-info/RECORD
