Metadata-Version: 2.4
Name: precice-config-visualizer
Version: 2.0.0
Summary: A tool for visualizing a preCICE configuration file as a dot file.
Author-email: The preCICE Developers <info@precice.org>
Maintainer-email: Frédéric Simonis <frederic.simonis@ipvs.uni-stuttgart.de>
License-Expression: MIT
Project-URL: Homepage, https://precice.org
Project-URL: Documentation, https://precice.org/tooling-config-visualization.html
Project-URL: Repository, https://github.com/precice/config-visualizer.git
Project-URL: Bug Tracker, https://github.com/precice/config-visualizer/issues
Keywords: preCICE,dot,graphviz,XML,configuration,visualization
Classifier: Development Status :: 4 - Beta
Classifier: Programming Language :: Python :: 3 :: Only
Classifier: Programming Language :: Python :: 3.8
Classifier: Topic :: Scientific/Engineering :: Visualization
Classifier: Topic :: Utilities
Requires-Python: >=3.8
License-File: LICENSE
Requires-Dist: lxml
Requires-Dist: pydot
Requires-Dist: typing_extensions
Provides-Extra: gui
Requires-Dist: precice-config-visualizer-gui; extra == "gui"
Dynamic: license-file
